[
  {
    "date": "2026-04-17",
    "topic": "Deservedly dead: On the defeat of the Constitution (131st Amendment) Bill, 2026",
    "source": "The Hindu",
    "mcq": {
      "question": "Deservedly dead: On the defeat of the Constitution (131st Amendment) Bill, 2026 is related to which of the following?",
      "options": [
        "Economy",
        "Polity",
        "Science & Tech",
        "Defence"
      ],
      "answer": "Polity",
      "subject": "Polity"
    }
  },
  {
    "date": "2026-04-17",
    "topic": "Allahabad HC orders FIR against Rahul Gandhi in alleged dual citizenship case",
    "source": "The Hindu",
    "mcq": {
      "question": "Allahabad HC orders FIR against Rahul Gandhi in alleged dual citizenship case is related to which of the following?",
      "options": [
        "Economy",
        "Polity",
        "Science & Tech",
        "Defence"
      ],
      "answer": "General Current Affairs",
      "subject": "General Current Affairs"
    }
  },
  {
    "date": "2026-04-17",
    "topic": "HC asks under what authority of law breath analyser test held on advocate",
    "source": "The Hindu",
    "mcq": {
      "question": "HC asks under what authority of law breath analyser test held on advocate is related to which of the following?",
      "options": [
        "Economy",
        "Polity",
        "Science & Tech",
        "Defence"
      ],
      "answer": "General Current Affairs",
      "subject": "General Current Affairs"
    }
  },
  {
    "date": "2026-04-17",
    "topic": "Higher education budget up by 60% in 5 years, yet T.N. govt. universities continue to struggle for funds",
    "source": "The Hindu",
    "mcq": {
      "question": "Higher education budget up by 60% in 5 years, yet T.N. govt. universities continue to struggle for funds is related to which of the following?",
      "options": [
        "Economy",
        "Polity",
        "Science & Tech",
        "Defence"
      ],
      "answer": "Economy",
      "subject": "Economy"
    }
  },
  {
    "date": "2026-04-17",
    "topic": "SC agrees to hear CBI\u2019s plea against HC order acquitting 4 in custodial-death case",
    "source": "The Hindu",
    "mcq": {
      "question": "SC agrees to hear CBI\u2019s plea against HC order acquitting 4 in custodial-death case is related to which of the following?",
      "options": [
        "Economy",
        "Polity",
        "Science & Tech",
        "Defence"
      ],
      "answer": "General Current Affairs",
      "subject": "General Current Affairs"
    }
  },
  {
    "date": "2026-04-17",
    "topic": "ADG visits NCC units in Kozhikode, Malappuram",
    "source": "The Hindu",
    "mcq": {
      "question": "ADG visits NCC units in Kozhikode, Malappuram is related to which of the following?",
      "options": [
        "Economy",
        "Polity",
        "Science & Tech",
        "Defence"
      ],
      "answer": "General Current Affairs",
      "subject": "General Current Affairs"
    }
  },
  {
    "date": "2026-04-17",
    "topic": "CCB unearths IPL tickets black market racket",
    "source": "The Hindu",
    "mcq": {
      "question": "CCB unearths IPL tickets black market racket is related to which of the following?",
      "options": [
        "Economy",
        "Polity",
        "Science & Tech",
        "Defence"
      ],
      "answer": "General Current Affairs",
      "subject": "General Current Affairs"
    }
  },
  {
    "date": "2026-04-17",
    "topic": "Income Tax officials search premises linked to Senthilbalaji\u2019s aides in Karur",
    "source": "The Hindu",
    "mcq": {
      "question": "Income Tax officials search premises linked to Senthilbalaji\u2019s aides in Karur is related to which of the following?",
      "options": [
        "Economy",
        "Polity",
        "Science & Tech",
        "Defence"
      ],
      "answer": "General Current Affairs",
      "subject": "General Current Affairs"
    }
  },
  {
    "date": "2026-04-17",
    "topic": "Constitution Amendment Bill, part of delimitation package, defeated",
    "source": "The Hindu",
    "mcq": {
      "question": "Constitution Amendment Bill, part of delimitation package, defeated is related to which of the following?",
      "options": [
        "Economy",
        "Polity",
        "Science & Tech",
        "Defence"
      ],
      "answer": "Polity",
      "subject": "Polity"
    }
  },
  {
    "date": "2026-04-17",
    "topic": "Nine people dead as van plunges off Valparai cliff in T.N.",
    "source": "The Hindu",
    "mcq": {
      "question": "Nine people dead as van plunges off Valparai cliff in T.N. is related to which of the following?",
      "options": [
        "Economy",
        "Polity",
        "Science & Tech",
        "Defence"
      ],
      "answer": "General Current Affairs",
      "subject": "General Current Affairs"
    }
  },
  {
    "date": "2026-04-17",
    "topic": "CPR awareness session held at Alwal Traffic Police Station under \u2018Alive Arrive\u2019 initiative",
    "source": "The Hindu",
    "mcq": {
      "question": "CPR awareness session held at Alwal Traffic Police Station under \u2018Alive Arrive\u2019 initiative is related to which of the following?",
      "options": [
        "Economy",
        "Polity",
        "Science & Tech",
        "Defence"
      ],
      "answer": "General Current Affairs",
      "subject": "General Current Affairs"
    }
  },
  {
    "date": "2026-04-17",
    "topic": "United Opposition defeated bid to harm Constitution: Kharge",
    "source": "The Hindu",
    "mcq": {
      "question": "United Opposition defeated bid to harm Constitution: Kharge is related to which of the following?",
      "options": [
        "Economy",
        "Polity",
        "Science & Tech",
        "Defence"
      ],
      "answer": "General Current Affairs",
      "subject": "General Current Affairs"
    }
  },
  {
    "date": "2026-04-17",
    "topic": "Chaturvedi\u2019s grumbling over defeat of Women\u2019s Bill\u2019 flies in the face of her party\u2019s stand",
    "source": "The Hindu",
    "mcq": {
      "question": "Chaturvedi\u2019s grumbling over defeat of Women\u2019s Bill\u2019 flies in the face of her party\u2019s stand is related to which of the following?",
      "options": [
        "Economy",
        "Polity",
        "Science & Tech",
        "Defence"
      ],
      "answer": "Polity",
      "subject": "Polity"
    }
  },
  {
    "date": "2026-04-17",
    "topic": "When a star madean impact on the poll outcome in\u00a0Tamil Nadu",
    "source": "The Hindu",
    "mcq": {
      "question": "When a star madean impact on the poll outcome in\u00a0Tamil Nadu is related to which of the following?",
      "options": [
        "Economy",
        "Polity",
        "Science & Tech",
        "Defence"
      ],
      "answer": "Polity",
      "subject": "Polity"
    }
  },
  {
    "date": "2026-04-17",
    "topic": "Nine killed as van carrying Malappuram schoolteachers plunges off Valparai cliff",
    "source": "The Hindu",
    "mcq": {
      "question": "Nine killed as van carrying Malappuram schoolteachers plunges off Valparai cliff is related to which of the following?",
      "options": [
        "Economy",
        "Polity",
        "Science & Tech",
        "Defence"
      ],
      "answer": "General Current Affairs",
      "subject": "General Current Affairs"
    }
  },
  {
    "date": "2026-04-17",
    "topic": "We know how to bring the debt under control, improve the finances of Tamil Nadu, and implement all the welfare schemes completely, says the AIADMK general secretary",
    "source": "The Hindu",
    "mcq": {
      "question": "We know how to bring the debt under control, improve the finances of Tamil Nadu, and implement all the welfare schemes completely, says the AIADMK general secretary is related to which of the following?",
      "options": [
        "Economy",
        "Polity",
        "Science & Tech",
        "Defence"
      ],
      "answer": "General Current Affairs",
      "subject": "General Current Affairs"
    }
  },
  {
    "date": "2026-04-17",
    "topic": "BJP to take to streets over defeat of women\u2019s quota Bill in Lok Sabha",
    "source": "The Hindu",
    "mcq": {
      "question": "BJP to take to streets over defeat of women\u2019s quota Bill in Lok Sabha is related to which of the following?",
      "options": [
        "Economy",
        "Polity",
        "Science & Tech",
        "Defence"
      ],
      "answer": "Polity",
      "subject": "Polity"
    }
  },
  {
    "date": "2026-04-17",
    "topic": "South stood united, made its voice heard and democracy prevailed: T.N. CM Stalin",
    "source": "The Hindu",
    "mcq": {
      "question": "South stood united, made its voice heard and democracy prevailed: T.N. CM Stalin is related to which of the following?",
      "options": [
        "Economy",
        "Polity",
        "Science & Tech",
        "Defence"
      ],
      "answer": "General Current Affairs",
      "subject": "General Current Affairs"
    }
  },
  {
    "date": "2026-04-17",
    "topic": "Opposition defeated an attack on the Constitution, says Rahul Gandhi",
    "source": "The Hindu",
    "mcq": {
      "question": "Opposition defeated an attack on the Constitution, says Rahul Gandhi is related to which of the following?",
      "options": [
        "Economy",
        "Polity",
        "Science & Tech",
        "Defence"
      ],
      "answer": "General Current Affairs",
      "subject": "General Current Affairs"
    }
  },
  {
    "date": "2026-04-17",
    "topic": "Watch: Constitution Amendment Bill, part of delimitation package, defeated",
    "source": "The Hindu",
    "mcq": {
      "question": "Watch: Constitution Amendment Bill, part of delimitation package, defeated is related to which of the following?",
      "options": [
        "Economy",
        "Polity",
        "Science & Tech",
        "Defence"
      ],
      "answer": "Polity",
      "subject": "Polity"
    }
  }
]